parade/__init__.py
parade/_spark.bak
parade/cmdline.py
parade/command/__init__.py
parade/command/convert.py
parade/command/init.py
parade/command/lab.py
parade/command/notebook.py
parade/command/server.py
parade/command/flow/__init__.py
parade/command/flow/create.py
parade/command/flow/list.py
parade/command/flow/rm.py
parade/command/flow/run.py
parade/command/task/__init__.py
parade/command/task/create.py
parade/command/task/list.py
parade/command/task/run.py
parade/config/__init__.py
parade/config/yaml.py
parade/core/__init__.py
parade/core/context.py
parade/core/engine.py
parade/core/recorder.py
parade/core/task.py
parade/datasource/__init__.py
parade/datasource/fake.py
parade/datasource/localfile.py
parade/datasource/rdb.py
parade/error/__init__.py
parade/error/flow_errors.py
parade/error/task_errors.py
parade/flowrunner/__init__.py
parade/flowrunner/default.py
parade/flowrunner/single.py
parade/flowstore/__init__.py
parade/flowstore/default.py
parade/notify/__init__.py
parade/notify/default.py
parade/server/__init__.py
parade/server/api/__init__.py
parade/server/api/data.py
parade/server/api/exec.py
parade/server/api/flow.py
parade/server/api/task.py
parade/server/auth/__init__.py
parade/server/auth/api.py
parade/server/dash/__init__.py
parade/server/dash/chart/__init__.py
parade/server/dash/chart/choropleth.py
parade/server/dash/chart/gantt.py
parade/server/dash/chart/indicator.py
parade/server/dash/chart/radar.py
parade/server/dash/filter/__init__.py
parade/server/dash/filter/date_range.py
parade/server/dash/filter/date_single.py
parade/server/dash/filter/selector.py
parade/server/dash/table/__init__.py
parade/server/dash/table/core.py
parade/server/dash/utils/__init__.py
parade/template/__init__.py
parade/template/task/__init__.py
parade/template/task/api.py.tpl
parade/template/task/etl.py.tpl
parade/template/task/setl.py.tpl
parade/template/workspace/__init__.py
parade/template/workspace/parade.bootstrap.yml
parade/template/workspace/parade.config.yml
parade-0.2.5.1.dist-info/LICENSE
parade-0.2.5.1.dist-info/METADATA
parade-0.2.5.1.dist-info/WHEEL
parade-0.2.5.1.dist-info/entry_points.txt
parade-0.2.5.1.dist-info/top_level.txt
parade-0.2.5.1.dist-info/RECORD
